cli.py
git.py
kahoot.py
git_kahoot-0.2.3.dist-info/METADATA
git_kahoot-0.2.3.dist-info/WHEEL
git_kahoot-0.2.3.dist-info/entry_points.txt
git_kahoot-0.2.3.dist-info/top_level.txt
git_kahoot-0.2.3.dist-info/RECORD
