Metadata-Version: 2.1
Name: git-kahoot
Version: 0.2.3
Summary: Generate a Kahoot quiz from commits in a git repository
Home-page: https://github.com/janerist/git-kahoot
Author: Jan-Erik Strøm
Author-email: jan.erik.strom@gmail.com
License: UNKNOWN
Platform: UNKNOWN
Classifier: Programming Language :: Python :: 3
Classifier: License :: OSI Approved :: MIT License
Classifier: Operating System :: OS Independent
Requires-Dist: Click (==8.0.1)
Requires-Dist: requests (==2.25.1)
